oblivious/__init__.py
oblivious/bn254.py
oblivious/ristretto.py
oblivious-7.0.0.dist-info/LICENSE
oblivious-7.0.0.dist-info/METADATA
oblivious-7.0.0.dist-info/WHEEL
oblivious-7.0.0.dist-info/top_level.txt
oblivious-7.0.0.dist-info/RECORD
