Metadata-Version: 2.1
Name: oblivious
Version: 7.0.0
Summary: Python library that serves as an API for common cryptographic primitives used to implement OPRF, OT, and PSI protocols.
Author: Nth Party
Author-email: team@nthparty.com
License: MIT
Project-URL: Repository, https://github.com/nthparty/oblivious
Project-URL: Documentation, https://oblivious.readthedocs.io
Requires-Python: >=3.7
License-File: LICENSE
Requires-Dist: parts (~=1.6)
Requires-Dist: fe25519 (~=1.4)
Requires-Dist: ge25519 (~=1.4)
Requires-Dist: bn254 (~=0.1)
Provides-Extra: coveralls
Requires-Dist: coveralls (~=3.3.1) ; extra == 'coveralls'
Provides-Extra: docs
Requires-Dist: toml (~=0.10.2) ; extra == 'docs'
Requires-Dist: sphinx (~=4.2.0) ; extra == 'docs'
Requires-Dist: sphinx-rtd-theme (~=1.0.0) ; extra == 'docs'
Provides-Extra: lint
Requires-Dist: pylint (~=2.17.0) ; extra == 'lint'
Provides-Extra: mclbn256
Requires-Dist: mclbn256 (~=1.3) ; extra == 'mclbn256'
Provides-Extra: publish
Requires-Dist: build (~=0.10) ; extra == 'publish'
Requires-Dist: twine (~=4.0) ; extra == 'publish'
Provides-Extra: rbcl
Requires-Dist: rbcl (~=1.0) ; extra == 'rbcl'
Provides-Extra: test
Requires-Dist: pytest (~=7.2) ; extra == 'test'
Requires-Dist: pytest-cov (~=4.0) ; extra == 'test'
Requires-Dist: bitlist (~=1.1) ; extra == 'test'
Requires-Dist: fountains (~=2.1) ; extra == 'test'
